<?xml version="1.0" encoding="utf-8"?>
<!DOCTYPE hibernate-mapping PUBLIC "-//Hibernate/Hibernate Mapping DTD 3.0//EN"
"http://www.hibernate.org/dtd/hibernate-mapping-3.0.dtd">
<!-- Mapping file autogenerated by MyEclipse Persistence Tools -->
<hibernate-mapping>
	<class name="net.cxp.entity.Product" table="PRODUCT" schema="CXP">
		<!-- usage中配置缓存策略，当两个并发的事务可以对他同时读，但是如果一个事务对他写的话，另外一个事务就不能读 -->
		<!-- bean中定义实体类 -->
		<cache usage="read-write" region="net.cxp.entity.Product" />
		<id name="id" type="java.lang.Integer">
			<column name="ID" precision="10" scale="0" />
			<generator class="sequence">
				<param name="sequence">seq_pid </param>
			</generator>
		</id>
		<!--延迟加载默认为true，初始化时由于会话在dao层已关闭所以在视图层显示时会因为拿不到数据而报错(could not initialize 
			proxy - no Session)解决方案： lazy="false" fetch="join" -->
		<many-to-one name="category" class="net.cxp.entity.Category"
			lazy="false" fetch="join">
			<column name="CID" precision="22" scale="0" />
		</many-to-one>
		<property name="name" type="java.lang.String">
			<column name="NAME" length="50" />
		</property>
		<property name="price" type="java.lang.Double">
			<column name="PRICE" precision="8" />
		</property>
		<property name="pic" type="java.lang.String">
			<column name="PIC" length="300" />
		</property>
		<property name="remark" type="java.lang.String">
			<column name="REMARK" length="50" />
		</property>
		<property name="xremark" type="java.lang.String">
			<column name="XREMARK" length="100" />
		</property>
		<property name="pdate" type="java.util.Date">
			<column name="PDATE" length="7" />
		</property>
		<property name="commend" type="java.lang.Integer">
			<column name="COMMEND" precision="2" scale="0" />
		</property>
		<property name="open" type="java.lang.Integer">
			<column name="OPEN" precision="2" scale="0" />
		</property>
		<set name="sorders" inverse="true">
			<key>
				<column name="PID" precision="22" scale="0" />
			</key>
			<one-to-many class="net.cxp.entity.Sorder" />
		</set>
	</class>
</hibernate-mapping>
